{"Writes":{"index.html":"2132378177","inkscape.html":"1089341355","jquery.validate.min.js":"2127611475","sitemap.xml":"1818589866","bootstrap.bundle.min.js":"1177607323","slack.html":"-1816403428","jquery.validate.js":"779258511","bootstrap.min.js":"-930007373","others.html":"353704182","site.js":"-1644681119","bootstrap.min.css":"2119736499","site.css":"-1261026509","vscode.html":"-1241748498","matlab.html":"-75324729","latex.html":"1455761572","jquery.min.js":"1710148599"},"Content":{"index.html":"680983089","inkscape.html":"-898856837","jquery.validate.min.js":"960200939","sitemap.xml":"-748827531","bootstrap.bundle.min.js":"-361991547","slack.html":"1019047080","jquery.validate.js":"-1953869480","bootstrap.min.js":"1831981440","others.html":"-1599445192","site.js":"2080012299","bootstrap.min.css":"46435639","site.css":"-150457450","vscode.html":"161810610","matlab.html":"-1981493729","latex.html":"168464347","jquery.min.js":"1108728673"}}